{
  "parent": "minecraft:recipes/root",
  "requirements": [
    [
      "has_the_recipe",
      "has_the_item"
    ]
  ],
  "criteria": {
    "has_the_recipe": {
      "trigger": "minecraft:recipe_unlocked",
      "conditions": {
        "recipe": "tomsmodcore:plate_alt12"
      }
    },
    "has_the_item": {
      "trigger": "minecraft:inventory_changed",
      "conditions": {
        "items": [
          {
            "item": "minecraft:gold_ingot",
            "data": 0
          }
        ]
      }
    }
  },
  "rewards": {
    "recipes": [
      "tomsmodcore:plate_alt12"
    ]
  }
}